{"code":"6520071","data":[{"prefcode":"28","ja":{"prefecture":"兵庫県","address1":"神戸市北区","address2":"山田町下谷上","address3":"","address4":""},"ja_kana":{"prefecture":"ﾋｮｳｺﾞｹﾝ","address1":"ｺｳﾍﾞｼｷﾀｸ","address2":"ﾔﾏﾀﾞﾁｮｳｼﾓﾀﾆｶﾞﾐ","address3":"","address4":""},"en":{"prefecture":"Hyogo","address1":"Kita-ku, Kobe-shi","address2":"Yamadachoshimotanigami","address3":"","address4":""}},{"prefcode":"28","ja":{"prefecture":"兵庫県","address1":"神戸市北区","address2":"念仏堂、ひよどり越）","address3":"","address4":""},"ja_kana":{"prefecture":"ﾋｮｳｺﾞｹﾝ","address1":"ｺｳﾍﾞｼｷﾀｸ","address2":"ﾈﾝﾌﾞﾂﾄﾞｳ､ﾋﾖﾄﾞﾘｺﾞｴ)","address3":"","address4":""},"en":{"prefecture":"Hyogo","address1":"Kita-ku, Kobe-shi","address2":"Nembutsudo.hiyodorigoe)","address3":"","address4":""}}]}
