{"code":"0880341","data":[{"prefcode":"01","ja":{"prefecture":"北海道","address1":"白糠郡白糠町","address2":"大苗","address3":"","address4":""},"ja_kana":{"prefecture":"ﾎｯｶｲﾄﾞｳ","address1":"ｼﾗﾇｶｸﾞﾝｼﾗﾇｶﾁｮｳ","address2":"ｵｵﾅｴ","address3":"","address4":""},"en":{"prefecture":"","address1":"","address2":"","address3":"","address4":""}},{"prefcode":"01","ja":{"prefecture":"北海道","address1":"白糠郡白糠町","address2":"下茶路","address3":"","address4":""},"ja_kana":{"prefecture":"ﾎｯｶｲﾄﾞｳ","address1":"ｼﾗﾇｶｸﾞﾝｼﾗﾇｶﾁｮｳ","address2":"ｼﾓﾁｬﾛ","address3":"","address4":""},"en":{"prefecture":"","address1":"","address2":"","address3":"","address4":""}},{"prefcode":"01","ja":{"prefecture":"北海道","address1":"白糠郡白糠町","address2":"相互","address3":"","address4":""},"ja_kana":{"prefecture":"ﾎｯｶｲﾄﾞｳ","address1":"ｼﾗﾇｶｸﾞﾝｼﾗﾇｶﾁｮｳ","address2":"ｿｳｺﾞ","address3":"","address4":""},"en":{"prefecture":"","address1":"","address2":"","address3":"","address4":""}},{"prefcode":"01","ja":{"prefecture":"北海道","address1":"白糠郡白糠町","address2":"西茶路","address3":"","address4":""},"ja_kana":{"prefecture":"ﾎｯｶｲﾄﾞｳ","address1":"ｼﾗﾇｶｸﾞﾝｼﾗﾇｶﾁｮｳ","address2":"ﾆｼﾁｬﾛ","address3":"","address4":""},"en":{"prefecture":"","address1":"","address2":"","address3":"","address4":""}},{"prefcode":"01","ja":{"prefecture":"北海道","address1":"白糠郡白糠町","address2":"東茶路","address3":"","address4":""},"ja_kana":{"prefecture":"ﾎｯｶｲﾄﾞｳ","address1":"ｼﾗﾇｶｸﾞﾝｼﾗﾇｶﾁｮｳ","address2":"ﾋｶﾞｼﾁｬﾛ","address3":"","address4":""},"en":{"prefecture":"","address1":"","address2":"","address3":"","address4":""}}]}
