{"code":"9870413","data":[{"prefcode":"04","ja":{"prefecture":"宮城県","address1":"登米市","address2":"南方町上原","address3":"","address4":""},"ja_kana":{"prefecture":"ﾐﾔｷﾞｹﾝ","address1":"ﾄﾒｼ","address2":"ﾐﾅﾐｶﾀﾏﾁｶﾐﾊﾗ","address3":"","address4":""},"en":{"prefecture":"Miyagi","address1":"Tome-shi","address2":"Minamikatamachi-kamihara","address3":"","address4":""}},{"prefcode":"04","ja":{"prefecture":"宮城県","address1":"登米市","address2":"南方町下原前","address3":"","address4":""},"ja_kana":{"prefecture":"ﾐﾔｷﾞｹﾝ","address1":"ﾄﾒｼ","address2":"ﾐﾅﾐｶﾀﾏﾁｼﾓﾊﾗﾏｴ","address3":"","address4":""},"en":{"prefecture":"Miyagi","address1":"Tome-shi","address2":"Minamikatamachi-shimoharamae","address3":"","address4":""}},{"prefcode":"04","ja":{"prefecture":"宮城県","address1":"登米市","address2":"南方町宿畑","address3":"","address4":""},"ja_kana":{"prefecture":"ﾐﾔｷﾞｹﾝ","address1":"ﾄﾒｼ","address2":"ﾐﾅﾐｶﾀﾏﾁｼｭｸﾊﾞﾀ","address3":"","address4":""},"en":{"prefecture":"Miyagi","address1":"Tome-shi","address2":"Minamikatamachi-shukubata","address3":"","address4":""}},{"prefcode":"04","ja":{"prefecture":"宮城県","address1":"登米市","address2":"南方町中原","address3":"","address4":""},"ja_kana":{"prefecture":"ﾐﾔｷﾞｹﾝ","address1":"ﾄﾒｼ","address2":"ﾐﾅﾐｶﾀﾏﾁﾅｶﾊﾗ","address3":"","address4":""},"en":{"prefecture":"Miyagi","address1":"Tome-shi","address2":"Minamikatamachi-nakahara","address3":"","address4":""}},{"prefcode":"04","ja":{"prefecture":"宮城県","address1":"登米市","address2":"南方町原","address3":"","address4":""},"ja_kana":{"prefecture":"ﾐﾔｷﾞｹﾝ","address1":"ﾄﾒｼ","address2":"ﾐﾅﾐｶﾀﾏﾁﾊﾗ","address3":"","address4":""},"en":{"prefecture":"Miyagi","address1":"Tome-shi","address2":"Minamikatamachi-hara","address3":"","address4":""}},{"prefcode":"04","ja":{"prefecture":"宮城県","address1":"登米市","address2":"南方町原浦","address3":"","address4":""},"ja_kana":{"prefecture":"ﾐﾔｷﾞｹﾝ","address1":"ﾄﾒｼ","address2":"ﾐﾅﾐｶﾀﾏﾁﾊﾗｳﾗ","address3":"","address4":""},"en":{"prefecture":"Miyagi","address1":"Tome-shi","address2":"Minamikatamachi-haraura","address3":"","address4":""}},{"prefcode":"04","ja":{"prefecture":"宮城県","address1":"登米市","address2":"南方町原前","address3":"","address4":""},"ja_kana":{"prefecture":"ﾐﾔｷﾞｹﾝ","address1":"ﾄﾒｼ","address2":"ﾐﾅﾐｶﾀﾏﾁﾊﾗﾏｴ","address3":"","address4":""},"en":{"prefecture":"Miyagi","address1":"Tome-shi","address2":"Minamikatamachi-haramae","address3":"","address4":""}},{"prefcode":"04","ja":{"prefecture":"宮城県","address1":"登米市","address2":"南方町原屋敷","address3":"","address4":""},"ja_kana":{"prefecture":"ﾐﾔｷﾞｹﾝ","address1":"ﾄﾒｼ","address2":"ﾐﾅﾐｶﾀﾏﾁﾊﾗﾔｼｷ","address3":"","address4":""},"en":{"prefecture":"Miyagi","address1":"Tome-shi","address2":"Minamikatamachi-harayashiki","address3":"","address4":""}}]}
