{"code":"6695328","data":[{"prefcode":"28","ja":{"prefecture":"兵庫県","address1":"豊岡市","address2":"日高町西芝","address3":"","address4":""},"ja_kana":{"prefecture":"ﾋｮｳｺﾞｹﾝ","address1":"ﾄﾖｵｶｼ","address2":"ﾋﾀﾞｶﾁｮｳﾆｼｼﾊﾞ","address3":"","address4":""},"en":{"prefecture":"Hyogo","address1":"Toyoka-shi","address2":"Hidakacho-nishishiba","address3":"","address4":""}},{"prefcode":"28","ja":{"prefecture":"兵庫県","address1":"豊岡市","address2":"日高町東芝","address3":"","address4":""},"ja_kana":{"prefecture":"ﾋｮｳｺﾞｹﾝ","address1":"ﾄﾖｵｶｼ","address2":"ﾋﾀﾞｶﾁｮｳﾋｶﾞｼｼﾊﾞ","address3":"","address4":""},"en":{"prefecture":"Hyogo","address1":"Toyoka-shi","address2":"Hidakacho-higashishiba","address3":"","address4":""}}]}
